openai_api_with_easy_tools_and_web_browsing.py
openai_api_with_easy_tools_and_web_browsing-1.0.7.dist-info/LICENSE
openai_api_with_easy_tools_and_web_browsing-1.0.7.dist-info/METADATA
openai_api_with_easy_tools_and_web_browsing-1.0.7.dist-info/WHEEL
openai_api_with_easy_tools_and_web_browsing-1.0.7.dist-info/top_level.txt
openai_api_with_easy_tools_and_web_browsing-1.0.7.dist-info/RECORD
