Metadata-Version: 2.1
Name: openai_api_with_easy_tools_and_web_browsing
Version: 1.0.7
Summary: An unofficial OpenAI library for Python, featuring an integrated Bing Custom Search API for web browsing (free) and easy-to-use custom tools
Author-email: ThomLecha <hamster12@hotmail.fr>
Project-URL: Homepage, https://github.com/ThomLecha/openai-api-with-easy-tools-and-web-browsing
Project-URL: Issues, https://github.com/ThomLecha/openai-api-with-easy-tools-and-web-browsing/issues
Classifier: Programming Language :: Python :: 3
Classifier: License :: OSI Approved :: MIT License
Classifier: Operating System :: OS Independent
Requires-Python: >=3.8
License-File: LICENSE
Requires-Dist: openai >=1.30.1
Requires-Dist: requests >=2.31.0
